langlayer.py
langlayer-0.1.0.dist-info/METADATA
langlayer-0.1.0.dist-info/WHEEL
langlayer-0.1.0.dist-info/top_level.txt
langlayer-0.1.0.dist-info/RECORD
