Metadata-Version: 2.4
Name: langlayer
Version: 0.1.0
Summary: Composable tools for building LLM-powered apps
Author-email: Your Name <karimlahlou.kl@gmail.com>
Requires-Python: >=3.8
